persian_localizations/__init__.py
persian_localizations/persian_localizations.py
persian_localizations-0.0.2.dist-info/LICENSE
persian_localizations-0.0.2.dist-info/METADATA
persian_localizations-0.0.2.dist-info/WHEEL
persian_localizations-0.0.2.dist-info/top_level.txt
persian_localizations-0.0.2.dist-info/RECORD
