Metadata-Version: 2.1
Name: persian-localizations
Version: 0.0.2
Summary: A Python package to facilitate Persian language localizations
Author-email: Mohammad Ali Haghshenas <haghshenas_m_a@yahoo.com>
Project-URL: Homepage, https://github.com/H-MAli/persian-localizations
Classifier: Programming Language :: Python :: 3
Classifier: License :: OSI Approved :: Apache Software License
Classifier: Operating System :: OS Independent
Requires-Python: >=3.10
License-File: LICENSE
